splendid/__init__.py
splendid/itertools_recipies.py
splendid-1.1.0.dist-info/DESCRIPTION.rst
splendid-1.1.0.dist-info/METADATA
splendid-1.1.0.dist-info/RECORD
splendid-1.1.0.dist-info/WHEEL
splendid-1.1.0.dist-info/metadata.json
splendid-1.1.0.dist-info/top_level.txt
splendid-1.1.0.dist-info/zip-safe
