Metadata-Version: 2.0
Name: splendid
Version: 1.1.0
Summary: Splendid, a collection of useful, small python tools.
Home-page: https://github.com/pythoncircus/splendid
Author: Joachim Folz, Jörn Hees
Author-email: joachim.folz+splendid@gmail.com, splendid@joernhees.de
License: MIT
Keywords: splendid tools utils wrappers useful small often needed
Platform: UNKNOWN
Classifier: Development Status :: 4 - Beta
Classifier: Intended Audience :: Developers
Classifier: License :: OSI Approved :: MIT License
Classifier: Programming Language :: Python :: 2.7
Classifier: Programming Language :: Python :: 3.3
Classifier: Programming Language :: Python :: 3.4
Classifier: Programming Language :: Python :: 3.5
Classifier: Programming Language :: Python :: 3.6
Classifier: Topic :: Software Development
Classifier: Topic :: Utilities
Requires-Dist: six
